scorch/__init__.py
scorch/conll.py
scorch/main.py
scorch/scores.py
scorch-0.2.0.dist-info/LICENSE.md
scorch-0.2.0.dist-info/METADATA
scorch-0.2.0.dist-info/WHEEL
scorch-0.2.0.dist-info/entry_points.txt
scorch-0.2.0.dist-info/top_level.txt
scorch-0.2.0.dist-info/RECORD
