Metadata-Version: 2.1
Name: scorch
Version: 0.2.0
Summary: Alternative scorer for the CoNLL-2011/2012 shared tasks on coreference resolution.
Home-page: https://github.com/LoicGrobol/scorch
Author: Loïc Grobol
Author-email: loic.grobol@gmail.com
License: MIT
Keywords: nlp,coreference,metric,conll
Platform: UNKNOWN
Classifier: License :: OSI Approved :: MIT License
Classifier: Programming Language :: Python :: 3.8
Classifier: Environment :: Console
Requires-Python: >=3.7
Requires-Dist: docopt-ng (>=0.7)
Requires-Dist: numpy
Requires-Dist: scipy (>=0.17.0)
Requires-Dist: tqdm
